traceloggingdynamic/__init__.py
traceloggingdynamic/py.typed
traceloggingdynamic-1.0.1.dist-info/licenses/LICENSE
traceloggingdynamic-1.0.1.dist-info/METADATA
traceloggingdynamic-1.0.1.dist-info/WHEEL
traceloggingdynamic-1.0.1.dist-info/top_level.txt
traceloggingdynamic-1.0.1.dist-info/RECORD
