Metadata-Version: 2.4
Name: traceloggingdynamic
Version: 1.0.1
Summary: Generates Event Tracing for Windows events using TraceLogging
Home-page: https://github.com/microsoft/tracelogging
Author: Doug Cook
License: MIT License
Project-URL: Bug Tracker, https://github.com/microsoft/tracelogging/issues
Keywords: TraceLogging,ETW,TraceLoggingDynamic,events,tracing
Classifier: Programming Language :: Python :: 3
Classifier: License :: OSI Approved :: MIT License
Classifier: Operating System :: Microsoft :: Windows
Classifier: Intended Audience :: Developers
Classifier: Topic :: System :: Logging
Requires-Python: >=3.6
License-File: LICENSE
Dynamic: license-file
